lucid_cli/__init__.py
lucid_cli/agent.py
lucid_cli/auditor.py
lucid_cli/auth.py
lucid_cli/catalog.py
lucid_cli/client.py
lucid_cli/config.py
lucid_cli/environment.py
lucid_cli/main.py
lucid_cli/passport.py
lucid_cli-0.1.0.dist-info/METADATA
lucid_cli-0.1.0.dist-info/WHEEL
lucid_cli-0.1.0.dist-info/entry_points.txt
lucid_cli-0.1.0.dist-info/top_level.txt
lucid_cli-0.1.0.dist-info/RECORD
