Metadata-Version: 2.4
Name: lucid-cli
Version: 0.1.0
Summary: CLI for deploying and managing AI agents on the Lucid platform
Author-email: Lucid Team <engineering@lucid.ai>
Maintainer-email: Lucid Team <engineering@lucid.ai>
License: Apache-2.0
Project-URL: Homepage, https://lucid.ai
Project-URL: Documentation, https://docs.lucid.ai/cli
Project-URL: Repository, https://github.com/Lucid-Computing/lucid-monorepo
Project-URL: Changelog, https://github.com/Lucid-Computing/lucid-monorepo/blob/main/CHANGELOG.md
Project-URL: Bug Tracker, https://github.com/Lucid-Computing/lucid-monorepo/issues
Keywords: lucid,ai,agents,cli,tee,confidential-computing,deployment
Classifier: Development Status :: 4 - Beta
Classifier: Intended Audience :: Developers
Classifier: Environment :: Console
Classifier: License :: OSI Approved :: Apache Software License
Classifier: Operating System :: OS Independent
Classifier: Programming Language :: Python :: 3
Classifier: Programming Language :: Python :: 3.12
Classifier: Topic :: Software Development :: Libraries :: Python Modules
Classifier: Topic :: System :: Systems Administration
Classifier: Typing :: Typed
Requires-Python: >=3.12
Requires-Dist: httpx
Requires-Dist: pydantic
Requires-Dist: PyYAML
Requires-Dist: structlog
Requires-Dist: lucid-sdk
Requires-Dist: typer[all]<1.0.0,>=0.12.0
Requires-Dist: httpx-sse<1.0.0,>=0.4.0
Requires-Dist: docker<8.0.0,>=7.0.0
